gridlooper/__init__.py
gridlooper/gridlooper.py
gridlooper/setup.py
gridlooper-0.0.2.dist-info/LICENSE
gridlooper-0.0.2.dist-info/METADATA
gridlooper-0.0.2.dist-info/WHEEL
gridlooper-0.0.2.dist-info/top_level.txt
gridlooper-0.0.2.dist-info/RECORD
