Metadata-Version: 2.1
Name: gridlooper
Version: 0.0.2
Summary: A tool to run experiments based on defined grid and function with single iteration.
Author: Kyrylo Mordan
Author-email: parachute.repo@gmail.com
Classifier: Development Status :: 3 - Alpha
Classifier: Intended Audience :: Developers
Classifier: Intended Audience :: Science/Research
Classifier: Programming Language :: Python :: 3
Classifier: Programming Language :: Python :: 3.9
Classifier: Programming Language :: Python :: 3.10
Classifier: Programming Language :: Python :: 3.11
Classifier: License :: OSI Approved :: MIT License
Classifier: Topic :: Scientific/Engineering
License-File: LICENSE
Requires-Dist: dill ==0.3.7
Requires-Dist: tqdm
Requires-Dist: attrs >=22.2.0
